aistudioredis/__init__.py
aistudioredis/connection.py
aistudioredis/exceptions.py
aistudioredis/hashmaps.py
aistudioredis/lists.py
aistudioredis/parsing.py
aistudioredis/sets.py
aistudioredis/sorted_sets.py
aistudioredis/validations.py
aistudioredis-0.1.0.dist-info/WHEEL
aistudioredis-0.1.0.dist-info/METADATA
aistudioredis-0.1.0.dist-info/RECORD
