Metadata-Version: 2.1
Name: aistudioredis
Version: 0.1.0
Summary: 
Author: dashsubhadeep
Author-email: dash.subhadeep@automationedge.com
Requires-Python: >=3.9,<4.0
Classifier: Programming Language :: Python :: 3
Classifier: Programming Language :: Python :: 3.10
Classifier: Programming Language :: Python :: 3.9
Requires-Dist: redis (>=4.3.4,<5.0.0)
